{
  "match": 1450401658734514308,
  "equipoA": "team1",
  "equipoB": "team2",
  "estado": "Pick & Ban",
  "turno": "A",
  "accion": "ban",
  "modo": "Overload",
  "mapas": [
    {
      "slot": 1,
      "modo": "HP",
      "mapa": "Den",
      "estado": "pick",
      "equipo": "A",
      "bandoA": "Defensa",
      "bandoB": "Ataque"
    },
    {
      "slot": 2,
      "modo": "SnD",
      "mapa": "Colossus",
      "estado": "pick",
      "equipo": "B",
      "bandoA": "Defensa",
      "bandoB": "Ataque"
    },
    {
      "slot": 4,
      "modo": "HP",
      "mapa": "Exposure",
      "estado": "pick",
      "equipo": "B",
      "bandoA": "Ataque",
      "bandoB": "Defensa"
    },
    {
      "slot": 5,
      "modo": "SnD",
      "mapa": "Raid",
      "estado": "pick",
      "equipo": "A",
      "bandoA": "Defensa",
      "bandoB": "Ataque"
    },
    {
      "slot": null,
      "modo": "HP",
      "mapa": "Colossus",
      "estado": "ban",
      "equipo": "A",
      "bandoA": null,
      "bandoB": null
    },
    {
      "slot": null,
      "modo": "HP",
      "mapa": "Blackheart",
      "estado": "ban",
      "equipo": "B",
      "bandoA": null,
      "bandoB": null
    },
    {
      "slot": null,
      "modo": "SnD",
      "mapa": "Exposure",
      "estado": "ban",
      "equipo": "B",
      "bandoA": null,
      "bandoB": null
    },
    {
      "slot": null,
      "modo": "SnD",
      "mapa": "Den",
      "estado": "ban",
      "equipo": "A",
      "bandoA": null,
      "bandoB": null
    }
  ],
  "resultados": [],
  "scoreA": 0,
  "scoreB": 0
}